README.md
ndix/.ipynb_checkpoints/Untitled-checkpoint.ipynb
ndix/Untitled.ipynb
ndix/__init__.py
ndix/src/dict.py
ndix-0.1.2.dist-info/WHEEL
ndix-0.1.2.dist-info/METADATA
ndix-0.1.2.dist-info/RECORD
