Metadata-Version: 2.1
Name: ndix
Version: 0.1.2
Summary: 
Home-page: https://github.com/mi92/ndix
License: BSD-3-Clause
Author: Michael Moor
Requires-Python: >=3.9,<4.0
Classifier: License :: OSI Approved :: BSD License
Classifier: Programming Language :: Python :: 3
Classifier: Programming Language :: Python :: 3.10
Classifier: Programming Language :: Python :: 3.9
Project-URL: Repository, https://github.com/mi92/ndix
